fantasy_formula/__init__.py
fantasy_formula/config.py
fantasy_formula/main.py
fantasy_formula/models.py
fantasy_formula/cli/__init__.py
fantasy_formula/cli/main.py
fantasy_formula/data/__init__.py
fantasy_formula/data/fetch.py
fantasy_formula/data/preprocess.py
fantasy_formula/examples/__init__.py
fantasy_formula/examples/basic_usage.py
fantasy_formula/scoring/__init__.py
fantasy_formula/scoring/constructors.py
fantasy_formula/scoring/drivers.py
fantasy_formula/scoring/rules_2025.py
fantasy_formula/tests/__init__.py
fantasy_formula/tests/test_models.py
fantasy_formula/tests/test_scoring_rules.py
fantasy_formula/utils/__init__.py
fantasy_formula/utils/classification.py
fantasy_formula/utils/driver_status.py
fantasy_formula/utils/overtake_calc.py
fantasy_formula/utils/pitstops.py
fantasy_formula-0.1.0.dist-info/licenses/LICENSE
fantasy_formula-0.1.0.dist-info/METADATA
fantasy_formula-0.1.0.dist-info/WHEEL
fantasy_formula-0.1.0.dist-info/entry_points.txt
fantasy_formula-0.1.0.dist-info/top_level.txt
fantasy_formula-0.1.0.dist-info/RECORD
