Metadata-Version: 2.4
Name: fantasy-formula
Version: 0.1.0
Summary: A Python library for calculating Fantasy Formula 1 points based on real F1 race data
Author: Josh Bruce
License: MIT
Project-URL: Homepage, https://github.com/JoshCBruce/fantasy-formula
Project-URL: Repository, https://github.com/JoshCBruce/fantasy-formula.git
Project-URL: Issues, https://github.com/JoshCBruce/fantasy-formula/issues
Classifier: Development Status :: 3 - Alpha
Classifier: Intended Audience :: Developers
Classifier: License :: OSI Approved :: MIT License
Classifier: Programming Language :: Python :: 3
Classifier: Programming Language :: Python :: 3.9
Classifier: Programming Language :: Python :: 3.10
Classifier: Programming Language :: Python :: 3.11
Classifier: Programming Language :: Python :: 3.12
Requires-Python: >=3.9
License-File: LICENSE
Requires-Dist: fastf1>=3.1.0
Requires-Dist: pandas>=1.5.0
Requires-Dist: numpy>=1.20.0
Requires-Dist: requests>=2.28.0
Requires-Dist: click>=8.0.0
Requires-Dist: dataclasses-json>=0.6.0
Provides-Extra: dev
Requires-Dist: pytest>=7.0.0; extra == "dev"
Requires-Dist: pytest-cov>=4.0.0; extra == "dev"
Requires-Dist: black>=22.0.0; extra == "dev"
Requires-Dist: isort>=5.10.0; extra == "dev"
Requires-Dist: flake8>=5.0.0; extra == "dev"
Requires-Dist: mypy>=1.0.0; extra == "dev"
Dynamic: license-file
